sphinx_express/__init__.py
sphinx_express/configs.py
sphinx_express/core.py
sphinx_express/models.py
sphinx_express/startup.py
sphinx_express/templates.py
sphinx_express/versions.py
sphinx_express-0.2.4.dist-info/LICENSE.txt
sphinx_express-0.2.4.dist-info/METADATA
sphinx_express-0.2.4.dist-info/WHEEL
sphinx_express-0.2.4.dist-info/entry_points.txt
sphinx_express-0.2.4.dist-info/top_level.txt
sphinx_express-0.2.4.dist-info/RECORD
